simple_collatz/__init__.py
simple_collatz/__main__.py
simple_collatz/__version__.py
simple_collatz/math_utils/__init__.py
simple_collatz-1.2.0.dist-info/METADATA
simple_collatz-1.2.0.dist-info/WHEEL
simple_collatz-1.2.0.dist-info/entry_points.txt
simple_collatz-1.2.0.dist-info/top_level.txt
simple_collatz-1.2.0.dist-info/RECORD
