Metadata-Version: 2.1
Name: simple-collatz
Version: 1.2.0
Summary: A simple collatz conjecture generator.
Home-page: https://github.com/appcreatorguy/collatz
Author: Manas Mengle
License: MIT
Project-URL: Changelog, https://github.com/appcreatorguy/collatz/blob/master/CHANGES.md
Keywords: simple_collatz collatz discrete math number theory
Platform: UNKNOWN
Classifier: Development Status :: 4 - Beta
Classifier: Environment :: Console
Classifier: Intended Audience :: Education
Classifier: Programming Language :: Python
Classifier: Programming Language :: Python :: 3.9
Classifier: Programming Language :: Python :: 3 :: Only
Classifier: Topic :: Scientific/Engineering :: Mathematics
Classifier: Topic :: Scientific/Engineering :: Visualization
Requires-Python: >=3.9.5
Requires-Dist: matplotlib (>=3.4.2)
Requires-Dist: appdirs (>=1.4.4)
